databank_x/__init__.py
databank_x-0.0.1.dist-info/METADATA
databank_x-0.0.1.dist-info/WHEEL
databank_x-0.0.1.dist-info/licenses/LICENSE
databank_x-0.0.1.dist-info/RECORD
