Metadata-Version: 2.4
Name: databank_x
Version: 0.0.1
Summary: A minimalistic, extensible database and encryption toolkit for Python
Project-URL: Homepage, https://github.com/Micro444/databank-x
Project-URL: Issues, https://github.com/Micro444/databank-x/issues
Author-email: Micro444 <example@example.com>
License: MIT License
License-File: LICENSE
Classifier: License :: OSI Approved :: MIT License
Classifier: Operating System :: OS Independent
Classifier: Programming Language :: Python :: 3
Requires-Python: >=3.0
Requires-Dist: cryptography
Requires-Dist: numpy<1.27
Requires-Dist: openpyxl
Requires-Dist: pandas
